{
    "predictions": [
        {
            "description": "192 Phố Lê Thanh Nghị, Đồng Tâm, Hai Bà Trưng, Hà Nội, Việt Nam",
            "place_id": "ChIJf8sJKnGsNTERy5eWGiJ4dRE",
            "reference": "ChIJf8sJKnGsNTERy5eWGiJ4dRE",
            "structured_formatting": {
                "main_text": "192 Phố Lê Thanh Nghị",
                "secondary_text": "Đồng Tâm, Hai Bà Trưng, Hà Nội, Việt Nam"
            }
        },
        {
            "description": "192 Phố Lê Trọng Tấn, Định Công, Hai Bà Trưng, Hà Nội, Việt Nam",
            "place_id": "ChIJkRWEWmKsNTERFjLi6NW2ucY",
            "reference": "ChIJkRWEWmKsNTERFjLi6NW2ucY",
            "structured_formatting": {
                "main_text": "192 Phố Lê Trọng Tấn",
                "secondary_text": "Định Công, Hai Bà Trưng, Hà Nội, Việt Nam"
            }
        },
        {
            "description": "300 Phố Bạch Mai, Bạch Mai, Hai Bà Trưng, Hà Nội, Việt Nam",
            "place_id": "ChIJg3IfnHSsNTERMcRyAPRk9so",
            "reference": "ChIJg3IfnHSsNTERMcRyAPRk9so",
            "structured_formatting": {
                "main_text": "300 Phố Bạch Mai",
                "secondary_text": "Bạch Mai, Hai Bà Trưng, Hà Nội, Việt Nam"
            }
        },
        {
            "description": "282 Phố Xã Đàn, Phương Liên, Đống Đa, Hà Nội, Việt Nam",
            "place_id": "EkcyODIgUGjhu5EgWMOjIMSQw6BuLCBQaMawxqFuZyBMacOqbiwgxJDhu5FuZyDEkGEsIEjDoCBO4buZaSwgVmnhu4d0IE5hbSIxEi8KFAoSCYHdlMSGqzUxEYS9bzIk4xceEJoCKhQKEglRaI3Lhqs1MRGbI1KNWMmnyA",
            "reference": "EkcyODIgUGjhu5EgWMOjIMSQw6BuLCBQaMawxqFuZyBMacOqbiwgxJDhu5FuZyDEkGEsIEjDoCBO4buZaSwgVmnhu4d0IE5hbSIxEi8KFAoSCYHdlMSGqzUxEYS9bzIk4xceEJoCKhQKEglRaI3Lhqs1MRGbI1KNWMmnyA",
            "structured_formatting": {
                "main_text": "282 Phố Xã Đàn",
                "secondary_text": "Phương Liên, Đống Đa, Hà Nội, Việt Nam"
            }
        },
        {
            "description": "192 Lê Thánh Tông, sĐông Vệ, Thành phố Thanh Hóa, Thanh Hoá, Việt Nam",
            "place_id": "ChIJGbT5veFXNjERcfbzzF-diug",
            "reference": "ChIJGbT5veFXNjERcfbzzF-diug",
            "structured_formatting": {
                "main_text": "192 Lê Thánh Tông",
                "secondary_text": "Đông Vệ, Thành phố Thanh Hóa, Thanh Hoá, Việt Nam"
            }
        }
    ],
    "status": "OK"
}